md_to_docx/__init__.py
md_to_docx/core.py
md_to_docx/server.py
md_to_docx-0.1.8.dist-info/licenses/LICENSE
md_to_docx-0.1.8.dist-info/METADATA
md_to_docx-0.1.8.dist-info/WHEEL
md_to_docx-0.1.8.dist-info/entry_points.txt
md_to_docx-0.1.8.dist-info/top_level.txt
md_to_docx-0.1.8.dist-info/RECORD
