Metadata-Version: 2.4
Name: md-to-docx
Version: 0.1.8
Summary: Convert Markdown to DOCX with support for Mermaid diagrams
Author-email: Your Name <lishangyin.lsy@outlook.com>
License: MIT
Project-URL: Homepage, https://github.com/yourusername/md-to-docx
Project-URL: Bug Tracker, https://github.com/yourusername/md-to-docx/issues
Keywords: markdown,docx,mermaid,converter
Classifier: Development Status :: 4 - Beta
Classifier: Intended Audience :: Developers
Classifier: License :: OSI Approved :: MIT License
Classifier: Programming Language :: Python :: 3
Classifier: Programming Language :: Python :: 3.8
Classifier: Programming Language :: Python :: 3.9
Classifier: Programming Language :: Python :: 3.10
Classifier: Programming Language :: Python :: 3.11
Classifier: Topic :: Text Processing :: Markup
Requires-Python: >=3.8
License-File: LICENSE
Requires-Dist: httpx>=0.28.1
Requires-Dist: mcp[cli]>=1.3.0
Requires-Dist: markdown>=3.7
Requires-Dist: python-docx>=1.1.2
Requires-Dist: beautifulsoup4>=4.13.3
Requires-Dist: pillow>=11.1.0
Requires-Dist: requests>=2.32.3
Dynamic: license-file
